transperth/__init__.py
transperth/exceptions.py
transperth/livetimes.py
transperth/assets/train_stations.json
transperth/jp/__init__.py
transperth/jp/fares.py
transperth/jp/location.py
transperth/jp/route_parser.py
transperth/jp/routes.py
transperth/jp/utils.py
transperth/silver_rails/__init__.py
transperth/silver_rails/reference_data.py
transperth/silver_rails/timetable.py
transperth/silver_rails/utils.py
transperth/smart_rider/__init__.py
transperth/smart_rider/post_back.py
transperth/smart_rider/smart_rider.py
transperth/smart_rider/trips.py
transperth-0.1.3.dist-info/LICENSE
transperth-0.1.3.dist-info/METADATA
transperth-0.1.3.dist-info/WHEEL
transperth-0.1.3.dist-info/top_level.txt
transperth-0.1.3.dist-info/RECORD
